geost/__init__.py
geost/_warnings.py
geost/abstract_classes.py
geost/base.py
geost/config.py
geost/data_objects.py
geost/enums.py
geost/header_factory.py
geost/mixins.py
geost/projections.py
geost/spatial.py
geost/utils.py
geost/analysis/__init__.py
geost/analysis/combine.py
geost/analysis/interpret_cpt.py
geost/analysis/layer_analysis.py
geost/bro/__init__.py
geost/bro/api.py
geost/bro/bro_cpt_geopackage.py
geost/bro/bro_geotop.py
geost/bro/bro_regis.py
geost/bro/bro_utils.py
geost/data/__init__.py
geost/data/registry.txt
geost/data/sample_data.py
geost/export/__init__.py
geost/export/geodataclass.py
geost/export/vtk.py
geost/io/__init__.py
geost/io/gef.py
geost/io/geopackage.py
geost/io/read.py
geost/io/parsers/__init__.py
geost/io/parsers/gef_parsers.py
geost/io/parsers/parser_utils.py
geost/io/parsers/xml_parsers.py
geost/io/xml/__init__.py
geost/io/xml/read.py
geost/io/xml/resolvers.py
geost/io/xml/schemas/__init__.py
geost/io/xml/schemas/bhrg.py
geost/io/xml/schemas/bhrgt.py
geost/io/xml/schemas/bhrp.py
geost/io/xml/schemas/cpt.py
geost/io/xml/schemas/sfr.py
geost/models/__init__.py
geost/models/basemodels.py
geost/models/model_utils.py
geost/validation/__init__.py
geost/validation/schemas.py
geost/validation/validate.py
geost-0.3.0.dist-info/METADATA
geost-0.3.0.dist-info/WHEEL
geost-0.3.0.dist-info/licenses/LICENSE
geost-0.3.0.dist-info/RECORD
