Metadata-Version: 2.4
Name: geost
Version: 0.3.0
Summary: The Python interface for geological point data in The Netherlands
Project-URL: Homepage, https://github.com/Deltares-research/geost
Project-URL: Repository, https://github.com/Deltares-research/geost
Project-URL: Issues, https://github.com/Deltares-research/geost/issues
Maintainer-email: Erik van Onselen <erik.vanonselen@deltares.nl>, Bas Knaake <bas.knaake@deltares.nl>
License: GNU LESSER GENERAL PUBLIC LICENSE
License-File: LICENSE
Keywords: borehole,bro,cpt,deltares,geology,geost,subsurface toolbox,well log
Classifier: Development Status :: 3 - Alpha
Classifier: Intended Audience :: Science/Research
Classifier: License :: OSI Approved :: GNU Lesser General Public License v3 (LGPLv3)
Classifier: Operating System :: OS Independent
Classifier: Programming Language :: Python
Classifier: Programming Language :: Python :: 3.12
Classifier: Programming Language :: Python :: 3.13
Classifier: Topic :: Scientific/Engineering
Requires-Python: >=3.12
Requires-Dist: geopandas
Requires-Dist: lxml
Requires-Dist: numpy
Requires-Dist: openpyxl
Requires-Dist: pandas
Requires-Dist: pandera
Requires-Dist: pooch
Requires-Dist: pyarrow
Requires-Dist: pyproj
Requires-Dist: pyvista
Requires-Dist: rioxarray
Requires-Dist: shapely
Requires-Dist: xlrd
